doc_handle/__init__.py
doc_handle-0.4.dist-info/DESCRIPTION.rst
doc_handle-0.4.dist-info/METADATA
doc_handle-0.4.dist-info/RECORD
doc_handle-0.4.dist-info/WHEEL
doc_handle-0.4.dist-info/metadata.json
doc_handle-0.4.dist-info/top_level.txt
