Metadata-Version: 2.0
Name: doc-handle
Version: 0.4
Summary: doc_handle a python module for working with .csv and .ods in python native
Home-page: UNKNOWN
Author: Javier Cabau Laporta
Author-email: jcabaulaporta@outlook.es
License: LICENSE
Platform: UNKNOWN
Classifier: Programming Language :: Python :: 3
Classifier: License :: OSI Approved :: GNU Library or Lesser General Public License (LGPL)
Classifier: Operating System :: OS Independent
Requires-Dist: numpy (>=1.16.2)
Requires-Dist: pyexcel-ods (>=0.5.6)
Requires-Dist: pyexcel (>=0.5.13)
